camera/HCNetSDK.py
camera/PlayCtrl.py
camera/__init__.py
camera/cam.py
camera/lib/linux/.gitkeep
camera/lib/linux/HCNetSDK_Log_Switch.xml
camera/lib/linux/libAudioRender.so
camera/lib/linux/libHCCore.so
camera/lib/linux/libNPQos.so
camera/lib/linux/libPlayCtrl.so
camera/lib/linux/libSuperRender.so
camera/lib/linux/libcrypto.so.1.1
camera/lib/linux/libhcnetsdk.so
camera/lib/linux/libhpr.so
camera/lib/linux/libopenal.so.1
camera/lib/linux/libssl.so.1.1
camera/lib/linux/libz.so
camera/lib/linux/HCNetSDKCom/libAudioIntercom.so
camera/lib/linux/HCNetSDKCom/libHCAlarm.so
camera/lib/linux/HCNetSDKCom/libHCCoreDevCfg.so
camera/lib/linux/HCNetSDKCom/libHCDisplay.so
camera/lib/linux/HCNetSDKCom/libHCGeneralCfgMgr.so
camera/lib/linux/HCNetSDKCom/libHCIndustry.so
camera/lib/linux/HCNetSDKCom/libHCPlayBack.so
camera/lib/linux/HCNetSDKCom/libHCPreview.so
camera/lib/linux/HCNetSDKCom/libHCVoiceTalk.so
camera/lib/linux/HCNetSDKCom/libStreamTransClient.so
camera/lib/linux/HCNetSDKCom/libSystemTransform.so
camera/lib/linux/HCNetSDKCom/libanalyzedata.so
camera/lib/linux/HCNetSDKCom/libiconv2.so
camera/lib/win/.gitkeep
camera/lib/win/AudioRender.dll
camera/lib/win/ClientDemo.exe
camera/lib/win/GdiPlus.dll
camera/lib/win/GdiPlus.lib
camera/lib/win/HCCore.dll
camera/lib/win/HCCore.lib
camera/lib/win/HCNetSDK.dll
camera/lib/win/HCNetSDK.lib
camera/lib/win/HXVA.dll
camera/lib/win/HmMerge.dll
camera/lib/win/LocalSensorAdd.dat
camera/lib/win/LocalXml.zip
camera/lib/win/MP_Render.dll
camera/lib/win/MP_VIE.dll
camera/lib/win/NPQos.dll
camera/lib/win/OpenAL32.dll
camera/lib/win/PlayCtrl.dll
camera/lib/win/PlayCtrl.lib
camera/lib/win/SuperRender.dll
camera/lib/win/YUVProcess.dll
camera/lib/win/hlog.dll
camera/lib/win/hpr.dll
camera/lib/win/libcrypto-1_1-x64.dll
camera/lib/win/libcrypto-1_1.dll
camera/lib/win/libmmd.dll
camera/lib/win/libssl-1_1-x64.dll
camera/lib/win/libssl-1_1.dll
camera/lib/win/zlib1.dll
camera/lib/win/HCNetSDKCom/AnalyzeData.dll
camera/lib/win/HCNetSDKCom/AudioIntercom.dll
hkcamera-1.0.1.dist-info/METADATA
hkcamera-1.0.1.dist-info/WHEEL
hkcamera-1.0.1.dist-info/top_level.txt
hkcamera-1.0.1.dist-info/RECORD
